windtools_mcp/__init__.py
windtools_mcp/__main__.py
windtools_mcp/server.py
windtools_mcp-1.2.1.dist-info/METADATA
windtools_mcp-1.2.1.dist-info/WHEEL
windtools_mcp-1.2.1.dist-info/entry_points.txt
windtools_mcp-1.2.1.dist-info/RECORD
