Metadata-Version: 2.4
Name: windtools-mcp
Version: 1.2.1
Summary: A Codebase MCP Tools
Author-email: ZahidGalea <zahidale.zg@gmail.com>
Classifier: License :: OSI Approved :: MIT License
Classifier: Operating System :: OS Independent
Classifier: Programming Language :: Python :: 3.10
Requires-Python: >=3.11
Requires-Dist: chromadb>=0.6.3
Requires-Dist: mcp>=1.4.1
Requires-Dist: sentence-transformers>=3.4.1
